visionseed/CameraExposureParams_pb2.py
visionseed/FaceDetectionResult_pb2.py
visionseed/FileListResult_pb2.py
visionseed/FilePart_pb2.py
visionseed/FlasherParams_pb2.py
visionseed/RegisterFaceIdWithPicParams_pb2.py
visionseed/SystemStatusResult_pb2.py
visionseed/YtDataLink.py
visionseed/YtFaceAlignment.py
visionseed/YtMsg_pb2.py
visionseed/YtVisionSeed.py
visionseed/__init__.py
visionseed-1.2.1.dist-info/LICENSE
visionseed-1.2.1.dist-info/METADATA
visionseed-1.2.1.dist-info/WHEEL
visionseed-1.2.1.dist-info/top_level.txt
visionseed-1.2.1.dist-info/RECORD
