Metadata-Version: 2.1
Name: visionseed
Version: 1.2.1
Summary: python-sdk for VisionSeed - a camera module with AI ability
Home-page: https://visionseed.youtu.qq.com
Author: liang chen
Author-email: chenliang@tencent.com
License: MIT
Platform: UNKNOWN
Classifier: License :: OSI Approved :: MIT License
Classifier: Programming Language :: Python :: 3
Classifier: Programming Language :: Python :: 3.7
Requires-Dist: pyserial
Requires-Dist: protobuf
Requires-Dist: numpy
